pycustomnets/__init__.py
pycustomnets/test.py
pycustomnets-1.1.0.dist-info/METADATA
pycustomnets-1.1.0.dist-info/WHEEL
pycustomnets-1.1.0.dist-info/licenses/LICENSE
pycustomnets-1.1.0.dist-info/RECORD
