Metadata-Version: 2.4
Name: pycustomnets
Version: 1.1.0
Summary: A Neural Network customization tool
Project-URL: Homepage, https://github.com/machinekeepslearning/pycustomnets
Project-URL: Issues, https://github.com/machinekeepslearning/pycustomnets/issues
Author-email: Raj <machinekeepslearning@gmail.com>
License-File: LICENSE
Classifier: License :: OSI Approved :: MIT License
Classifier: Operating System :: OS Independent
Classifier: Programming Language :: Python :: 3
Requires-Python: >=3.8
